[{"text": "<!-- Page 1 -->", "type": "frontmatter", "language": "english", "heading_level": null, "paragraph_type": null, "paragraph_level": null, "prefix": null, "action_verb": null, "action_verb_type": null, "action_verb_normalized": null, "links": []}, {"text": "General Assembly—Nineteenth Session", "type": "frontmatter", "language": "english", "heading_level": null, "paragraph_type": null, "paragraph_level": null, "prefix": null, "action_verb": null, "action_verb_type": null, "action_verb_normalized": null, "links": []}, {"text": "RESOLUTIONS ADOPTED WITHOUT REFERENCE TO A COMMITTEE", "type": "frontmatter", "language": "english", "heading_level": null, "paragraph_type": null, "paragraph_level": null, "prefix": null, "action_verb": null, "action_verb_type": null, "action_verb_normalized": null, "links": []}, {"text": "1994 (XIX). Confirmation of the allocation of funds for the Expanded Programme of Technical Assistance in 1965", "type": "frontmatter", "language": "english", "heading_level": null, "paragraph_type": null, "paragraph_level": null, "prefix": null, "action_verb": null, "action_verb_type": null, "action_verb_normalized": null, "links": []}, {"text": "The General Assembly,", "type": "frontmatter", "language": "english", "heading_level": null, "paragraph_type": null, "paragraph_level": null, "prefix": null, "action_verb": null, "action_verb_type": null, "action_verb_normalized": null, "links": []}, {"text": "Noting that the Technical Assistance Committee has reviewed and approved the Expanded Programme of Technical Assistance for the biennium 1965-1966,", "type": "frontmatter", "language": "english", "heading_level": null, "paragraph_type": null, "paragraph_level": null, "prefix": null, "action_verb": null, "action_verb_type": null, "action_verb_normalized": null, "links": []}, {"text": "1. Confirms the allocation of funds authorized by the Technical Assistance Committee to each of the organizations participating in the Expanded Programme of Technical Assistance from contributions, general resources and local costs assessments, as follows:", "type": "frontmatter", "language": "english", "heading_level": null, "paragraph_type": null, "paragraph_level": null, "prefix": null, "action_verb": null, "action_verb_type": null, "action_verb_normalized": null, "links": []}, {"text": "| Participating organization                          | Allocation (equivalent of U.S. dollars) |", "type": "frontmatter", "language": "english", "heading_level": null, "paragraph_type": null, "paragraph_level": null, "prefix": null, "action_verb": null, "action_verb_type": null, "action_verb_normalized": null, "links": []}, {"text": "|----------------------------------------------------|----------------------------------------|", "type": "frontmatter", "language": "english", "heading_level": null, "paragraph_type": null, "paragraph_level": null, "prefix": null, "action_verb": null, "action_verb_type": null, "action_verb_normalized": null, "links": []}, {"text": "| United Nations                                     | 11,154,714                             |", "type": "frontmatter", "language": "english", "heading_level": null, "paragraph_type": null, "paragraph_level": null, "prefix": null, "action_verb": null, "action_verb_type": null, "action_verb_normalized": null, "links": []}, {"text": "| International Labour Organisation                  | 5,909,792                              |", "type": "frontmatter", "language": "english", "heading_level": null, "paragraph_type": null, "paragraph_level": null, "prefix": null, "action_verb": null, "action_verb_type": null, "action_verb_normalized": null, "links": []}, {"text": "| Food and Agriculture Organization of the United Nations | 13,770,728                             |", "type": "frontmatter", "language": "english", "heading_level": null, "paragraph_type": null, "paragraph_level": null, "prefix": null, "action_verb": null, "action_verb_type": null, "action_verb_normalized": null, "links": []}, {"text": "| United Nations Educational, Scientific and Cultural Organization | 9,210,185                              |", "type": "frontmatter", "language": "english", "heading_level": null, "paragraph_type": null, "paragraph_level": null, "prefix": null, "action_verb": null, "action_verb_type": null, "action_verb_normalized": null, "links": []}, {"text": "| International Civil Aviation Organization         | 2,563,849                              |", "type": "frontmatter", "language": "english", "heading_level": null, "paragraph_type": null, "paragraph_level": null, "prefix": null, "action_verb": null, "action_verb_type": null, "action_verb_normalized": null, "links": []}, {"text": "| World Health Organization                          | 9,221,851                              |", "type": "frontmatter", "language": "english", "heading_level": null, "paragraph_type": null, "paragraph_level": null, "prefix": null, "action_verb": null, "action_verb_type": null, "action_verb_normalized": null, "links": []}, {"text": "| Universal Postal Union                             | 428,437                               |", "type": "frontmatter", "language": "english", "heading_level": null, "paragraph_type": null, "paragraph_level": null, "prefix": null, "action_verb": null, "action_verb_type": null, "action_verb_normalized": null, "links": []}, {"text": "| International Telecommunication Union             | 1,452,334                             |", "type": "frontmatter", "language": "english", "heading_level": null, "paragraph_type": null, "paragraph_level": null, "prefix": null, "action_verb": null, "action_verb_type": null, "action_verb_normalized": null, "links": []}, {"text": "| World Meteorological Organization                  | 1,484,987                             |", "type": "frontmatter", "language": "english", "heading_level": null, "paragraph_type": null, "paragraph_level": null, "prefix": null, "action_verb": null, "action_verb_type": null, "action_verb_normalized": null, "links": []}, {"text": "| Inter-Governmental Maritime Consultative Organization | 25,000                                |", "type": "frontmatter", "language": "english", "heading_level": null, "paragraph_type": null, "paragraph_level": null, "prefix": null, "action_verb": null, "action_verb_type": null, "action_verb_normalized": null, "links": []}, {"text": "| International Atomic Energy Agency                 | 1,083,991                             |", "type": "frontmatter", "language": "english", "heading_level": null, "paragraph_type": null, "paragraph_level": null, "prefix": null, "action_verb": null, "action_verb_type": null, "action_verb_normalized": null, "links": []}, {"text": "| TOTAL                                          | 56,305,865                        |", "type": "frontmatter", "language": "english", "heading_level": null, "paragraph_type": null, "paragraph_level": null, "prefix": null, "action_verb": null, "action_verb_type": null, "action_verb_normalized": null, "links": []}, {"text": "2. Concurs in the Committee’s authorization to the Executive Chairman of the Technical Assistance Board to make such changes in these allocations as may be necessary to provide, as far as possible, for the full utilization of contributions to the Expanded Programme of Technical Assistance, and to permit modifications to country programmes requested by recipient Governments and approved by him;", "type": "frontmatter", "language": "english", "heading_level": null, "paragraph_type": null, "paragraph_level": null, "prefix": null, "action_verb": null, "action_verb_type": null, "action_verb_normalized": null, "links": []}, {"text": "3. Requests the Executive Chairman to report any such changes to the Committee at the session following their adoption.", "type": "frontmatter", "language": "english", "heading_level": null, "paragraph_type": null, "paragraph_level": null, "prefix": null, "action_verb": null, "action_verb_type": null, "action_verb_normalized": null, "links": []}, {"text": "1314th plenary meeting,", "type": "frontmatter", "language": "english", "heading_level": null, "paragraph_type": null, "paragraph_level": null, "prefix": null, "action_verb": null, "action_verb_type": null, "action_verb_normalized": null, "links": []}, {"text": "30 December 1964.", "type": "frontmatter", "language": "english", "heading_level": null, "paragraph_type": null, "paragraph_level": null, "prefix": null, "action_verb": null, "action_verb_type": null, "action_verb_normalized": null, "links": []}, {"text": "1995 (XIX). Establishment of the United Nations Conference on Trade and Development as an organ of the General Assembly", "type": "title", "language": "english", "heading_level": null, "paragraph_type": null, "paragraph_level": null, "prefix": null, "action_verb": null, "action_verb_type": null, "action_verb_normalized": null, "links": []}, {"text": "The General Assembly,", "type": "paragraph", "language": "english", "heading_level": null, "paragraph_type": "preambular", "paragraph_level": null, "prefix": null, "action_verb": null, "action_verb_type": null, "action_verb_normalized": null, "links": []}, {"text": "Convinced that sustained efforts are necessary to raise the standards of living in all countries and to accelerate the economic growth of the developing countries,", "type": "paragraph", "language": "english", "heading_level": null, "paragraph_type": "preambular", "paragraph_level": null, "prefix": null, "action_verb": "Convinced", "action_verb_type": "preambular", "action_verb_normalized": null, "links": []}, {"text": "Considering that international trade is an important instrument for economic development,", "type": "paragraph", "language": "english", "heading_level": null, "paragraph_type": "preambular", "paragraph_level": null, "prefix": null, "action_verb": "Considering", "action_verb_type": "preambular", "action_verb_normalized": null, "links": []}, {"text": " See also note on this item on page 9.", "type": "paragraph", "language": "english", "heading_level": null, "paragraph_type": "preambular", "paragraph_level": null, "prefix": null, "action_verb": null, "action_verb_type": null, "action_verb_normalized": null, "links": []}, {"text": "Recognizing that the United Nations Conference on Trade and Development has provided a unique opportunity to make a comprehensive review of the problems of trade and of trade in relation to economic development, particularly those affecting the developing countries,", "type": "paragraph", "language": "english", "heading_level": null, "paragraph_type": "preambular", "paragraph_level": null, "prefix": null, "action_verb": "Recognizing", "action_verb_type": "preambular", "action_verb_normalized": null, "links": []}, {"text": "Convinced that adequate and effectively functioning organizational arrangements are essential if the full contribution of international trade to the accelerated economic growth of the developing countries is to be successfully realized through the formulation and implementation of the necessary policies,", "type": "paragraph", "language": "english", "heading_level": null, "paragraph_type": "preambular", "paragraph_level": null, "prefix": null, "action_verb": "Convinced", "action_verb_type": "preambular", "action_verb_normalized": null, "links": []}, {"text": "Taking into account that the operation of existing international institutions was examined by the United Nations Conference on Trade and Development, which recognized both their contributions and their limitations in dealing with all the problems of trade and related problems of development,", "type": "paragraph", "language": "english", "heading_level": null, "paragraph_type": "preambular", "paragraph_level": null, "prefix": null, "action_verb": "Taking", "action_verb_type": "preambular", "action_verb_normalized": null, "links": []}, {"text": "Believing that all States participating in the United Nations Conference on Trade and Development should make the most effective use of institutions and arrangements to which they are or may become parties,", "type": "paragraph", "language": "english", "heading_level": null, "paragraph_type": "preambular", "paragraph_level": null, "prefix": null, "action_verb": "Believing", "action_verb_type": "preambular", "action_verb_normalized": null, "links": []}, {"text": "Convinced that, at the same time, there should be a further review of both the present and the proposed institutional arrangements, in the light of the experience of their work and activities,", "type": "paragraph", "language": "english", "heading_level": null, "paragraph_type": "preambular", "paragraph_level": null, "prefix": null, "action_verb": "Convinced", "action_verb_type": "preambular", "action_verb_normalized": null, "links": []}, {"text": "Taking note of the widespread desire among developing countries for a comprehensive trade organization,", "type": "paragraph", "language": "english", "heading_level": null, "paragraph_type": "preambular", "paragraph_level": null, "prefix": null, "action_verb": "Taking", "action_verb_type": "preambular", "action_verb_normalized": null, "links": []}, {"text": "Recognizing that further institutional arrangements are necessary in order to continue the work initiated by the Conference and to implement its recommendations and conclusions,", "type": "paragraph", "language": "english", "heading_level": null, "paragraph_type": "preambular", "paragraph_level": null, "prefix": null, "action_verb": "Recognizing", "action_verb_type": "preambular", "action_verb_normalized": null, "links": []}, {"text": "", "type": "heading", "language": "english", "heading_level": 1, "paragraph_type": null, "paragraph_level": null, "prefix": "I", "action_verb": null, "action_verb_type": null, "action_verb_normalized": null, "links": []}, {"text": "Establishes the United Nations Conference on Trade and Development as an organ of the General Assembly in accordance with the provisions set forth in section II below;", "type": "paragraph", "language": "english", "heading_level": null, "paragraph_type": "preambular", "paragraph_level": null, "prefix": null, "action_verb": "Establishes", "action_verb_type": "operative", "action_verb_normalized": null, "links": []}, {"text": "", "type": "heading", "language": "english", "heading_level": 1, "paragraph_type": null, "paragraph_level": null, "prefix": "II", "action_verb": null, "action_verb_type": null, "action_verb_normalized": null, "links": []}, {"text": "The members of the United Nations Conference on Trade and Development (hereinafter referred to as the Conference) shall be those States which are Members of the United Nations or members of the specialized agencies or of the International Atomic Energy Agency.", "type": "paragraph", "language": "english", "heading_level": null, "paragraph_type": "operative", "paragraph_level": 1, "prefix": "1.", "action_verb": null, "action_verb_type": null, "action_verb_normalized": null, "links": []}, {"text": "The Conference shall be convened at intervals of not more than three years. The General Assembly shall determine the date and location of the sessions of the Conference, taking into account the recommendations of the Conference or of the Trade and Development Board established under paragraph 4 below.", "type": "paragraph", "language": "english", "heading_level": null, "paragraph_type": "operative", "paragraph_level": 1, "prefix": "2.", "action_verb": null, "action_verb_type": null, "action_verb_normalized": null, "links": []}, {"text": "The principal functions of the Conference shall be:", "type": "paragraph", "language": "english", "heading_level": null, "paragraph_type": "operative", "paragraph_level": 1, "prefix": "3.", "action_verb": null, "action_verb_type": null, "action_verb_normalized": null, "links": []}, {"text": "To promote international trade, especially with a view to accelerating economic development, particularly trade between countries at different stages of development, between developing countries and between countries with different systems of economic", "type": "paragraph", "language": "english", "heading_level": null, "paragraph_type": "operative", "paragraph_level": 2, "prefix": "(a)", "action_verb": null, "action_verb_type": null, "action_verb_normalized": null, "links": []}, {"text": "<!-- Page 2 -->", "type": "footer", "language": "english", "heading_level": null, "paragraph_type": null, "paragraph_level": null, "prefix": null, "action_verb": null, "action_verb_type": null, "action_verb_normalized": null, "links": []}, {"text": "2", "type": "footer", "language": "english", "heading_level": null, "paragraph_type": null, "paragraph_level": null, "prefix": null, "action_verb": null, "action_verb_type": null, "action_verb_normalized": null, "links": []}, {"text": "General Assembly—Nineteenth Session", "type": "paragraph", "language": "english", "heading_level": null, "paragraph_type": "preambular", "paragraph_level": null, "prefix": null, "action_verb": null, "action_verb_type": null, "action_verb_normalized": null, "links": []}, {"text": "and social organization, taking into account the functions performed by existing international organizations;", "type": "paragraph", "language": "english", "heading_level": null, "paragraph_type": "preambular", "paragraph_level": null, "prefix": null, "action_verb": null, "action_verb_type": null, "action_verb_normalized": null, "links": []}, {"text": "To formulate principles and policies on international trade and related problems of economic development;", "type": "paragraph", "language": "english", "heading_level": null, "paragraph_type": "preambular", "paragraph_level": 2, "prefix": "(b)", "action_verb": null, "action_verb_type": null, "action_verb_normalized": null, "links": []}, {"text": "To make proposals for putting the said principles and policies into effect and to take such other steps within its competence as may be relevant to this end, having regard to differences in economic systems and stages of development;", "type": "paragraph", "language": "english", "heading_level": null, "paragraph_type": "preambular", "paragraph_level": 2, "prefix": "(c)", "action_verb": null, "action_verb_type": null, "action_verb_normalized": null, "links": []}, {"text": "Generally, to review and facilitate the co-ordination of activities of other institutions within the United Nations system in the field of international trade and related problems of economic development, and in this regard to co-operate with the General Assembly and the Economic and Social Council with respect to the performance of their responsibilities for co-ordination under the Charter of the United Nations;", "type": "paragraph", "language": "english", "heading_level": null, "paragraph_type": "preambular", "paragraph_level": 2, "prefix": "(d)", "action_verb": null, "action_verb_type": null, "action_verb_normalized": null, "links": []}, {"text": "To initiate action, where appropriate, in cooperation with the competent organs of the United Nations for the negotiation and adoption of multilateral legal instruments in the field of trade, with due regard to the adequacy of existing organs of negotiation and without duplication of their activities;", "type": "paragraph", "language": "english", "heading_level": null, "paragraph_type": "preambular", "paragraph_level": 2, "prefix": "(e)", "action_verb": null, "action_verb_type": null, "action_verb_normalized": null, "links": []}, {"text": "To be available as a centre for harmonizing the trade and related development policies of Governments and regional economic groupings in pursuance of Article 1 of the Charter;", "type": "paragraph", "language": "english", "heading_level": null, "paragraph_type": "preambular", "paragraph_level": 2, "prefix": "(f)", "action_verb": null, "action_verb_type": null, "action_verb_normalized": null, "links": []}, {"text": "To deal with any other matters within the scope of its competence.", "type": "paragraph", "language": "english", "heading_level": null, "paragraph_type": "preambular", "paragraph_level": 2, "prefix": "(g)", "action_verb": null, "action_verb_type": null, "action_verb_normalized": null, "links": []}, {"text": "TRADE AND DEVELOPMENT BOARD", "type": "paragraph", "language": "english", "heading_level": null, "paragraph_type": "preambular", "paragraph_level": null, "prefix": null, "action_verb": null, "action_verb_type": null, "action_verb_normalized": null, "links": []}, {"text": "Composition", "type": "paragraph", "language": "english", "heading_level": null, "paragraph_type": "preambular", "paragraph_level": null, "prefix": null, "action_verb": null, "action_verb_type": null, "action_verb_normalized": null, "links": []}, {"text": "A permanent organ of the Conference, the Trade and Development Board (hereinafter referred to as the Board), shall be established as part of the United Nations machinery in the economic field.", "type": "paragraph", "language": "english", "heading_level": null, "paragraph_type": "operative", "paragraph_level": 1, "prefix": "4.", "action_verb": null, "action_verb_type": null, "action_verb_normalized": null, "links": []}, {"text": "The Board shall consist of fifty-five members elected by the Conference from among its membership. In electing the members of the Board, the Conference shall have full regard for both equitable geographical distribution and the desirability of continuing representation for the principal trading States, and shall accordingly observe the following distribution of seats:", "type": "paragraph", "language": "english", "heading_level": null, "paragraph_type": "operative", "paragraph_level": 1, "prefix": "5.", "action_verb": null, "action_verb_type": null, "action_verb_normalized": null, "links": []}, {"text": "Twenty-two from the States listed in part A of the annex to the present resolution;", "type": "paragraph", "language": "english", "heading_level": null, "paragraph_type": "operative", "paragraph_level": 2, "prefix": "(a)", "action_verb": null, "action_verb_type": null, "action_verb_normalized": null, "links": []}, {"text": "Eighteen from the States listed in part B of the annex;", "type": "paragraph", "language": "english", "heading_level": null, "paragraph_type": "operative", "paragraph_level": 2, "prefix": "(b)", "action_verb": null, "action_verb_type": null, "action_verb_normalized": null, "links": []}, {"text": "Nine from the States listed in part C of the annex;", "type": "paragraph", "language": "english", "heading_level": null, "paragraph_type": "operative", "paragraph_level": 2, "prefix": "(c)", "action_verb": null, "action_verb_type": null, "action_verb_normalized": null, "links": []}, {"text": "Six from the States listed in part D of the annex.", "type": "paragraph", "language": "english", "heading_level": null, "paragraph_type": "operative", "paragraph_level": 2, "prefix": "(d)", "action_verb": null, "action_verb_type": null, "action_verb_normalized": null, "links": []}, {"text": "The lists of States contained in the annex shall be reviewed periodically by the Conference in the light of changes in membership of the Conference and other factors.", "type": "paragraph", "language": "english", "heading_level": null, "paragraph_type": "operative", "paragraph_level": 1, "prefix": "6.", "action_verb": null, "action_verb_type": null, "action_verb_normalized": null, "links": []}, {"text": "The members of the Board shall be elected at each regular session of the Conference. They shall hold office until the election of their successors.", "type": "paragraph", "language": "english", "heading_level": null, "paragraph_type": "operative", "paragraph_level": 1, "prefix": "7.", "action_verb": null, "action_verb_type": null, "action_verb_normalized": null, "links": []}, {"text": "Retiring members shall be eligible for re-election.", "type": "paragraph", "language": "english", "heading_level": null, "paragraph_type": "operative", "paragraph_level": 1, "prefix": "8.", "action_verb": "Retiring", "action_verb_type": "preambular", "action_verb_normalized": null, "links": []}, {"text": "Each member of the Board shall have one representative with such alternate and advisers as may be required.", "type": "paragraph", "language": "english", "heading_level": null, "paragraph_type": "operative", "paragraph_level": 1, "prefix": "9.", "action_verb": null, "action_verb_type": null, "action_verb_normalized": null, "links": []}, {"text": "The Board shall invite any member of the Conference to participate, without vote, in its delibera-", "type": "paragraph", "language": "english", "heading_level": null, "paragraph_type": "operative", "paragraph_level": 1, "prefix": "10.", "action_verb": null, "action_verb_type": null, "action_verb_normalized": null, "links": []}, {"text": "tions on any matter of particular concern to that member.", "type": "paragraph", "language": "english", "heading_level": null, "paragraph_type": "preambular", "paragraph_level": null, "prefix": null, "action_verb": "tions", "action_verb_type": "operative", "action_verb_normalized": null, "links": []}, {"text": "The Board may make arrangements for representatives of the inter-governmental bodies referred to in paragraphs 18 and 19 below to participate, without vote, in its deliberations and in those of the subsidiary bodies and working groups established by it. Such participation may also be offered to non-governmental organizations concerned with matters of trade and of trade as related to development.", "type": "paragraph", "language": "english", "heading_level": null, "paragraph_type": "operative", "paragraph_level": 1, "prefix": "11.", "action_verb": null, "action_verb_type": null, "action_verb_normalized": null, "links": []}, {"text": "The Board shall adopt its own rules of procedure.", "type": "paragraph", "language": "english", "heading_level": null, "paragraph_type": "operative", "paragraph_level": 1, "prefix": "12.", "action_verb": null, "action_verb_type": null, "action_verb_normalized": null, "links": []}, {"text": "The Board shall meet as required in accordance with its rules. It shall normally meet twice in any particular year.", "type": "paragraph", "language": "english", "heading_level": null, "paragraph_type": "operative", "paragraph_level": 1, "prefix": "13.", "action_verb": null, "action_verb_type": null, "action_verb_normalized": null, "links": []}, {"text": "Functions", "type": "paragraph", "language": "english", "heading_level": null, "paragraph_type": "preambular", "paragraph_level": null, "prefix": null, "action_verb": "Functions", "action_verb_type": "operative", "action_verb_normalized": null, "links": []}, {"text": "When the Conference is not in session, the Board shall carry out the functions that fall within the competence of the Conference.", "type": "paragraph", "language": "english", "heading_level": null, "paragraph_type": "operative", "paragraph_level": 1, "prefix": "14.", "action_verb": null, "action_verb_type": null, "action_verb_normalized": null, "links": []}, {"text": "In particular, the Board shall keep under review and take appropriate action within its competence for the implementation of the recommendations, declarations, resolutions and other decisions of the Conference and for ensuring the continuity of its work.", "type": "paragraph", "language": "english", "heading_level": null, "paragraph_type": "operative", "paragraph_level": 1, "prefix": "15.", "action_verb": null, "action_verb_type": null, "action_verb_normalized": null, "links": []}, {"text": "The Board may make or initiate studies and reports in the field of trade and related problems of development.", "type": "paragraph", "language": "english", "heading_level": null, "paragraph_type": "operative", "paragraph_level": 1, "prefix": "16.", "action_verb": null, "action_verb_type": null, "action_verb_normalized": null, "links": []}, {"text": "The Board may request the Secretary-General of the United Nations to prepare such reports, studies or other documents as it may deem appropriate.", "type": "paragraph", "language": "english", "heading_level": null, "paragraph_type": "operative", "paragraph_level": 1, "prefix": "17.", "action_verb": null, "action_verb_type": null, "action_verb_normalized": null, "links": []}, {"text": "The Board shall, as required, make arrangements to obtain reports from and establish links with intergovernmental bodies whose activities are relevant to its functions. In order to avoid duplication it shall avail itself, whenever possible, of the relevant reports made to the Economic and Social Council and other United Nations bodies.", "type": "paragraph", "language": "english", "heading_level": null, "paragraph_type": "operative", "paragraph_level": 1, "prefix": "18.", "action_verb": null, "action_verb_type": null, "action_verb_normalized": null, "links": []}, {"text": "The Board shall establish close and continuous links with the regional economic commissions of the United Nations and may establish such links with other relevant regional inter-governmental bodies.", "type": "paragraph", "language": "english", "heading_level": null, "paragraph_type": "operative", "paragraph_level": 1, "prefix": "19.", "action_verb": null, "action_verb_type": null, "action_verb_normalized": null, "links": []}, {"text": "In its relations with organs and agencies within the United Nations system, the Board shall act in conformity with the responsibilities of the Economic and Social Council under the Charter, particularly those of co-ordination, and with the relationship agreements with the agencies concerned.", "type": "paragraph", "language": "english", "heading_level": null, "paragraph_type": "operative", "paragraph_level": 1, "prefix": "20.", "action_verb": null, "action_verb_type": null, "action_verb_normalized": null, "links": []}, {"text": "The Board shall serve as a preparatory committee for future sessions of the Conference. To that end, it shall initiate the preparation of documents, including a provisional agenda, for consideration by the Conference, as well as make recommendations as to the appropriate date and place for its convening.", "type": "paragraph", "language": "english", "heading_level": null, "paragraph_type": "operative", "paragraph_level": 1, "prefix": "21.", "action_verb": null, "action_verb_type": null, "action_verb_normalized": null, "links": []}, {"text": "The Board shall report to the Conference and it shall also report annually on its activities to the General Assembly through the Economic and Social Council. The Council may transmit to the Assembly such comments on the reports as it may deem necessary.", "type": "paragraph", "language": "english", "heading_level": null, "paragraph_type": "operative", "paragraph_level": 1, "prefix": "22.", "action_verb": null, "action_verb_type": null, "action_verb_normalized": null, "links": []}, {"text": "The Board shall establish such subsidiary organs as may be necessary to the effective discharge of its functions. It shall establish, in particular, the following committees:", "type": "paragraph", "language": "english", "heading_level": null, "paragraph_type": "operative", "paragraph_level": 1, "prefix": "23.", "action_verb": null, "action_verb_type": null, "action_verb_normalized": null, "links": []}, {"text": "A committee on commodities which, inter alia, will carry out the functions which are now performed by the Commission on International Commodity Trade and the Interim Co-ordinating", "type": "paragraph", "language": "english", "heading_level": null, "paragraph_type": "operative", "paragraph_level": 2, "prefix": "(a)", "action_verb": null, "action_verb_type": null, "action_verb_normalized": null, "links": []}, {"text": "<!-- Page 3 -->", "type": "footer", "language": "english", "heading_level": null, "paragraph_type": null, "paragraph_level": null, "prefix": null, "action_verb": null, "action_verb_type": null, "action_verb_normalized": null, "links": []}, {"text": "Resolutions adopted without reference to a Committee", "type": "paragraph", "language": "english", "heading_level": null, "paragraph_type": "preambular", "paragraph_level": null, "prefix": null, "action_verb": "Resolutions", "action_verb_type": "operative", "action_verb_normalized": null, "links": []}, {"text": "Committee for International Commodity Arrangements. In this connexion, the Interim Co-ordinating Committee shall be maintained as an advisory body of the Board;", "type": "paragraph", "language": "english", "heading_level": null, "paragraph_type": "preambular", "paragraph_level": null, "prefix": null, "action_verb": null, "action_verb_type": null, "action_verb_normalized": null, "links": []}, {"text": "A committee on manufactures;", "type": "paragraph", "language": "english", "heading_level": null, "paragraph_type": "preambular", "paragraph_level": 2, "prefix": "(b)", "action_verb": null, "action_verb_type": null, "action_verb_normalized": null, "links": []}, {"text": "A committee on invisibles and financing related to trade. The Board shall give special consideration to the appropriate institutional means for dealing with problems of shipping, and shall take into account the recommendations contained in annexes A.I.V.21 and A.IV.22 of the Final Act of the Conference.⁴", "type": "paragraph", "language": "english", "heading_level": null, "paragraph_type": "preambular", "paragraph_level": 2, "prefix": "(c)", "action_verb": null, "action_verb_type": null, "action_verb_normalized": null, "links": []}, {"text": "The terms of reference of the latter two subsidiary bodies and any other subsidiary organs established by the Board shall be adopted after consultation with the appropriate organs of the United Nations and shall take fully into account the desirability of avoiding duplication and overlapping of responsibilities. In determining the size of the subsidiary organs and in electing their members, the Board shall take fully into account the desirability of including in the membership of these bodies member States with a special interest in the subject-matter to be dealt with by them. It may include any State member of the Conference, whether or not that State is represented on the Board. The Board will determine the terms of reference and rules of procedure of its subsidiary organs.", "type": "paragraph", "language": "english", "heading_level": null, "paragraph_type": "preambular", "paragraph_level": null, "prefix": null, "action_verb": null, "action_verb_type": null, "action_verb_normalized": null, "links": []}, {"text": "VOTING", "type": "paragraph", "language": "english", "heading_level": null, "paragraph_type": "preambular", "paragraph_level": null, "prefix": null, "action_verb": null, "action_verb_type": null, "action_verb_normalized": null, "links": []}, {"text": "Each State represented at the Conference shall have one vote. Decisions of the Conference on matters of substance shall be taken by a two-thirds majority of the representatives present and voting. Decisions of the Conference on matters of procedure shall be taken by a majority of the representatives present and voting. Decisions of the Board shall be taken by a simple majority of the representatives present and voting.", "type": "paragraph", "language": "english", "heading_level": null, "paragraph_type": "operative", "paragraph_level": 1, "prefix": "24.", "action_verb": null, "action_verb_type": null, "action_verb_normalized": null, "links": []}, {"text": "PROCEDURES", "type": "paragraph", "language": "english", "heading_level": null, "paragraph_type": "preambular", "paragraph_level": null, "prefix": null, "action_verb": null, "action_verb_type": null, "action_verb_normalized": null, "links": []}, {"text": "The procedures set forth in the present paragraph are designed to provide a process of conciliation to take place before voting and to provide an adequate basis for the adoption of recommendations with regard to proposals of a specific nature for action substantially affecting the economic or financial interests of particular countries.", "type": "paragraph", "language": "english", "heading_level": null, "paragraph_type": "operative", "paragraph_level": 1, "prefix": "25.", "action_verb": null, "action_verb_type": null, "action_verb_normalized": null, "links": []}, {"text": "Levels of conciliation", "type": "paragraph", "language": "english", "heading_level": null, "paragraph_type": "operative", "paragraph_level": 2, "prefix": "(a)", "action_verb": "Levels", "action_verb_type": "operative", "action_verb_normalized": null, "links": []}, {"text": "The process of conciliation within the meaning of the present paragraph may take place under the conditions stated with regard to proposals which are before the Conference, the Board or Committees of the Board. In the case of Committees of the Board, the process of conciliation shall apply only to those matters, if any, with respect to which a Committee has been authorized to submit, without further approval, recommendations for action.", "type": "paragraph", "language": "english", "heading_level": null, "paragraph_type": "preambular", "paragraph_level": null, "prefix": null, "action_verb": null, "action_verb_type": null, "action_verb_normalized": null, "links": []}, {"text": "Request for conciliation", "type": "paragraph", "language": "english", "heading_level": null, "paragraph_type": "preambular", "paragraph_level": 2, "prefix": "(b)", "action_verb": null, "action_verb_type": null, "action_verb_normalized": null, "links": []}, {"text": "A request for conciliation within the meaning of the present paragraph may be made:", "type": "paragraph", "language": "english", "heading_level": null, "paragraph_type": "preambular", "paragraph_level": null, "prefix": null, "action_verb": null, "action_verb_type": null, "action_verb_normalized": null, "links": []}, {"text": "In the case of proposals before the Conference, by at least ten members of the Conference;", "type": "paragraph", "language": "english", "heading_level": null, "paragraph_type": "preambular", "paragraph_level": 2, "prefix": "(i)", "action_verb": null, "action_verb_type": null, "action_verb_normalized": null, "links": []}, {"text": "⁴ See Proceedings of the United Nations Conference on Trade and Development, vol. I, Final Act and Report (United Nations publication, Sales No.: 64.II.B.11), p. 54.", "type": "footer", "language": "english", "heading_level": null, "paragraph_type": null, "paragraph_level": null, "prefix": null, "action_verb": null, "action_verb_type": null, "action_verb_normalized": null, "links": []}, {"text": "(ii) In the case of proposals before the Board by at least five members of the Conference, whether or not they are members of the Board;", "type": "footer", "language": "english", "heading_level": null, "paragraph_type": null, "paragraph_level": null, "prefix": null, "action_verb": null, "action_verb_type": null, "action_verb_normalized": null, "links": []}, {"text": "(iii) In the case of proposals before Committees of the Board, by three members of the Committee.", "type": "footer", "language": "english", "heading_level": null, "paragraph_type": null, "paragraph_level": null, "prefix": null, "action_verb": null, "action_verb_type": null, "action_verb_normalized": null, "links": []}, {"text": "The request for conciliation under the present paragraph shall be submitted, as appropriate, to the President of the Conference or to the Chairman of the Board. In the case of a request relating to a proposal before a Committee of the Board, the Chairman of the Committee concerned shall submit the request to the Chairman of the Board.", "type": "footer", "language": "english", "heading_level": null, "paragraph_type": null, "paragraph_level": null, "prefix": null, "action_verb": null, "action_verb_type": null, "action_verb_normalized": null, "links": []}, {"text": "(c) Initiation of conciliation by the President or Chairman", "type": "footer", "language": "english", "heading_level": null, "paragraph_type": null, "paragraph_level": null, "prefix": null, "action_verb": null, "action_verb_type": null, "action_verb_normalized": null, "links": []}, {"text": "The process of conciliation within the meaning of the present paragraph may also be initiated whenever the President of the Conference, the Chairman of the Board or the Chairman of the Committee concerned is satisfied that the required number of countries as specified in sub-paragraph (b) above are in favour of such conciliation. In cases where the process of conciliation is initiated at the level of a Committee, the Chairman of the Committee concerned shall refer the matter to the Chairman of the Board for action to be taken in accordance with sub-paragraph (f) below.", "type": "footer", "language": "english", "heading_level": null, "paragraph_type": null, "paragraph_level": null, "prefix": null, "action_verb": null, "action_verb_type": null, "action_verb_normalized": null, "links": []}, {"text": "(d) Time for request or initiation of conciliation", "type": "footer", "language": "english", "heading_level": null, "paragraph_type": null, "paragraph_level": null, "prefix": null, "action_verb": null, "action_verb_type": null, "action_verb_normalized": null, "links": []}, {"text": "The request for conciliation (or the initiation of conciliation by the President or the Chairman, as the case may be) may be made only after the debate on the proposal has been concluded within the organ concerned and prior to the vote on that proposal. For the purposes of this provision, the Chairman of the organ concerned shall, at the conclusion of the debate on any proposal, afford an appropriate interval for the submission of requests for conciliation before proceeding to the vote on the proposal in question. In the event that conciliation is requested or initiated, voting on the proposal in question shall be suspended and the procedures provided for below shall be followed.", "type": "footer", "language": "english", "heading_level": null, "paragraph_type": null, "paragraph_level": null, "prefix": null, "action_verb": null, "action_verb_type": null, "action_verb_normalized": null, "links": []}, {"text": "(e) Subjects in regard to which conciliation is appropriate or excluded", "type": "footer", "language": "english", "heading_level": null, "paragraph_type": null, "paragraph_level": null, "prefix": null, "action_verb": null, "action_verb_type": null, "action_verb_normalized": null, "links": []}, {"text": "The institution of the process of conciliation shall be automatic under the conditions stated in sub-paragraphs (b) and (c) above. The categories in (i) and (ii) below shall serve as guidelines:", "type": "footer", "language": "english", "heading_level": null, "paragraph_type": null, "paragraph_level": null, "prefix": null, "action_verb": null, "action_verb_type": null, "action_verb_normalized": null, "links": []}, {"text": "(i) Appropriate for conciliation shall be proposals of a specific nature for action substantially affecting the economic or financial interests of particular countries in the following fields:", "type": "footer", "language": "english", "heading_level": null, "paragraph_type": null, "paragraph_level": null, "prefix": null, "action_verb": null, "action_verb_type": null, "action_verb_normalized": null, "links": []}, {"text": "- Economic plans or programmes or economic or social readjustments;", "type": "footer", "language": "english", "heading_level": null, "paragraph_type": null, "paragraph_level": null, "prefix": null, "action_verb": null, "action_verb_type": null, "action_verb_normalized": null, "links": []}, {"text": "- Trade, monetary or tariff policies, or balance of payments;", "type": "footer", "language": "english", "heading_level": null, "paragraph_type": null, "paragraph_level": null, "prefix": null, "action_verb": null, "action_verb_type": null, "action_verb_normalized": null, "links": []}, {"text": "- Policies of economic assistance or transfer of resources;", "type": "footer", "language": "english", "heading_level": null, "paragraph_type": null, "paragraph_level": null, "prefix": null, "action_verb": null, "action_verb_type": null, "action_verb_normalized": null, "links": []}, {"text": "- Levels of employment, income, revenue or investment;", "type": "footer", "language": "english", "heading_level": null, "paragraph_type": null, "paragraph_level": null, "prefix": null, "action_verb": null, "action_verb_type": null, "action_verb_normalized": null, "links": []}, {"text": "- Rights or obligations under international agreements or treaties.", "type": "footer", "language": "english", "heading_level": null, "paragraph_type": null, "paragraph_level": null, "prefix": null, "action_verb": null, "action_verb_type": null, "action_verb_normalized": null, "links": []}, {"text": "(ii) Proposals in the following fields shall not require conciliation:", "type": "footer", "language": "english", "heading_level": null, "paragraph_type": null, "paragraph_level": null, "prefix": null, "action_verb": null, "action_verb_type": null, "action_verb_normalized": null, "links": []}, {"text": "- Any procedural matter;", "type": "footer", "language": "english", "heading_level": null, "paragraph_type": null, "paragraph_level": null, "prefix": null, "action_verb": null, "action_verb_type": null, "action_verb_normalized": null, "links": []}, {"text": "<!-- Page 4 -->", "type": "footer", "language": "english", "heading_level": null, "paragraph_type": null, "paragraph_level": null, "prefix": null, "action_verb": null, "action_verb_type": null, "action_verb_normalized": null, "links": []}, {"text": "4", "type": "footer", "language": "english", "heading_level": null, "paragraph_type": null, "paragraph_level": null, "prefix": null, "action_verb": null, "action_verb_type": null, "action_verb_normalized": null, "links": []}, {"text": "General Assembly—Nineteenth Session", "type": "paragraph", "language": "english", "heading_level": null, "paragraph_type": "preambular", "paragraph_level": null, "prefix": null, "action_verb": null, "action_verb_type": null, "action_verb_normalized": null, "links": []}, {"text": "Any proposal for study or investigation, including such proposals related to the preparation of legal instruments in the field of trade;", "type": "paragraph", "language": "english", "heading_level": null, "paragraph_type": "preambular", "paragraph_level": null, "prefix": null, "action_verb": null, "action_verb_type": null, "action_verb_normalized": null, "links": []}, {"text": "Establishment of subsidiary bodies of the Board within the scope of its competence;", "type": "paragraph", "language": "english", "heading_level": null, "paragraph_type": "preambular", "paragraph_level": null, "prefix": null, "action_verb": null, "action_verb_type": null, "action_verb_normalized": null, "links": []}, {"text": "Recommendations and declarations of a general character not calling for specific action;", "type": "paragraph", "language": "english", "heading_level": null, "paragraph_type": "preambular", "paragraph_level": null, "prefix": null, "action_verb": "Recommendations", "action_verb_type": "operative", "action_verb_normalized": null, "links": []}, {"text": "Proposals involving action proposed in pursuance of recommendations which were unanimously adopted by the Conference.", "type": "paragraph", "language": "english", "heading_level": null, "paragraph_type": "preambular", "paragraph_level": null, "prefix": null, "action_verb": "Proposals", "action_verb_type": "operative", "action_verb_normalized": null, "links": []}, {"text": "Nomination of a conciliation committee", "type": "paragraph", "language": "english", "heading_level": null, "paragraph_type": "preambular", "paragraph_level": 2, "prefix": "(f)", "action_verb": null, "action_verb_type": null, "action_verb_normalized": null, "links": []}, {"text": "When a request for conciliation is made or initiated, the presiding officer of the organ concerned shall immediately inform the organ. The President of the Conference or the Chairman of the Board shall, as soon as possible, after consultation with the members of the organ concerned, nominate the members of a conciliation committee and submit the nominations for the approval of the Conference or the Board, as appropriate.", "type": "paragraph", "language": "english", "heading_level": null, "paragraph_type": "preambular", "paragraph_level": null, "prefix": null, "action_verb": null, "action_verb_type": null, "action_verb_normalized": null, "links": []}, {"text": "Size and composition of the conciliation committee", "type": "paragraph", "language": "english", "heading_level": null, "paragraph_type": "preambular", "paragraph_level": 2, "prefix": "(g)", "action_verb": null, "action_verb_type": null, "action_verb_normalized": null, "links": []}, {"text": "The conciliation committee shall, as a rule, be small in size. Its members shall include countries especially interested in the matter with respect to which such conciliation was initiated and shall be selected on an equitable geographical basis.", "type": "paragraph", "language": "english", "heading_level": null, "paragraph_type": "preambular", "paragraph_level": null, "prefix": null, "action_verb": null, "action_verb_type": null, "action_verb_normalized": null, "links": []}, {"text": "Procedure within the conciliation committee and submission of its report", "type": "paragraph", "language": "english", "heading_level": null, "paragraph_type": "preambular", "paragraph_level": 2, "prefix": "(h)", "action_verb": null, "action_verb_type": null, "action_verb_normalized": null, "links": []}, {"text": "The conciliation committee shall begin its work as soon as possible and it shall endeavour to reach agreement during the same session of the Conference or the Board. No vote shall take place in the conciliation committee. In the event that the conciliation committee is unable to conclude its work or fails to reach agreement at the same session of the Conference or of the Board, it shall report to the next session of the Board or of the Conference, whichever meets earlier. However, the Conference may instruct the conciliation committee appointed by it to submit its report to the following session of the Conference in the event that the committee shall not have concluded its work or shall have failed to reach agreement during the same session of the Conference.", "type": "paragraph", "language": "english", "heading_level": null, "paragraph_type": "preambular", "paragraph_level": null, "prefix": null, "action_verb": null, "action_verb_type": null, "action_verb_normalized": null, "links": []}, {"text": "Extension of the mandate of the conciliation committee", "type": "paragraph", "language": "english", "heading_level": null, "paragraph_type": "preambular", "paragraph_level": 2, "prefix": "(i)", "action_verb": null, "action_verb_type": null, "action_verb_normalized": null, "links": []}, {"text": "A proposal to continue a conciliation committee beyond the session at which it is required to report shall be decided by a simple majority.", "type": "paragraph", "language": "english", "heading_level": null, "paragraph_type": "preambular", "paragraph_level": null, "prefix": null, "action_verb": null, "action_verb_type": null, "action_verb_normalized": null, "links": []}, {"text": "Report of the conciliation committee", "type": "paragraph", "language": "english", "heading_level": null, "paragraph_type": "preambular", "paragraph_level": 2, "prefix": "(j)", "action_verb": null, "action_verb_type": null, "action_verb_normalized": null, "links": []}, {"text": "The report of the conciliation committee shall indicate whether or not the committee was able to reach an agreement and whether or not the committee recommends a further period of conciliation. The report of the committee shall be made available to the members of the Conference.", "type": "paragraph", "language": "english", "heading_level": null, "paragraph_type": "preambular", "paragraph_level": null, "prefix": null, "action_verb": null, "action_verb_type": null, "action_verb_normalized": null, "links": []}, {"text": "Action on the report of the conciliation committee", "type": "paragraph", "language": "english", "heading_level": null, "paragraph_type": "preambular", "paragraph_level": 2, "prefix": "(k)", "action_verb": null, "action_verb_type": null, "action_verb_normalized": null, "links": []}, {"text": "The report of the conciliation committee shall have priority on the agenda of the organ to which it is submitted. If the organ adopts a resolution on the proposal which was the subject of the report of the conciliation committee, that resolution shall refer explicitly to the report of the conciliation committee and to the conclusion reached by the conciliation committee in the following form, as appropriate:", "type": "paragraph", "language": "english", "heading_level": null, "paragraph_type": "preambular", "paragraph_level": null, "prefix": null, "action_verb": null, "action_verb_type": null, "action_verb_normalized": null, "links": []}, {"text": "“Noting the report of the Conciliation Committee appointed on (date) (document number),", "type": "paragraph", "language": "english", "heading_level": null, "paragraph_type": "preambular", "paragraph_level": null, "prefix": null, "action_verb": "“Noting", "action_verb_type": "preambular", "action_verb_normalized": null, "links": []}, {"text": "“Noting also that the Conciliation Committee [was able to reach an agreement] [recommends a further period of conciliation] [was unable to reach agreement],”", "type": "paragraph", "language": "english", "heading_level": null, "paragraph_type": "preambular", "paragraph_level": null, "prefix": null, "action_verb": "“Noting", "action_verb_type": "preambular", "action_verb_normalized": null, "links": []}, {"text": "Reports of the Board and of the Conference", "type": "paragraph", "language": "english", "heading_level": null, "paragraph_type": "preambular", "paragraph_level": 2, "prefix": "(l)", "action_verb": "Reports", "action_verb_type": "operative", "action_verb_normalized": null, "links": []}, {"text": "The reports of the Board to the Conference and to the General Assembly and the reports of the Conference to the Assembly shall include, inter alia:", "type": "paragraph", "language": "english", "heading_level": null, "paragraph_type": "preambular", "paragraph_level": null, "prefix": null, "action_verb": null, "action_verb_type": null, "action_verb_normalized": null, "links": []}, {"text": "The texts of all recommendations, resolutions and declarations adopted by the Board or the Conference during the period covered by the report;", "type": "paragraph", "language": "english", "heading_level": null, "paragraph_type": "preambular", "paragraph_level": 2, "prefix": "(i)", "action_verb": null, "action_verb_type": null, "action_verb_normalized": null, "links": []}, {"text": "In respect of recommendations and resolutions which are adopted after a process of conciliation, there shall also be included a record of the voting on each recommendation or resolution, together with the texts of the reports of the conciliation committees concerned. In the report, the record of voting and the texts of the reports shall normally follow the resolutions to which they pertain.", "type": "paragraph", "language": "english", "heading_level": null, "paragraph_type": "preambular", "paragraph_level": 3, "prefix": "(ii)", "action_verb": null, "action_verb_type": null, "action_verb_normalized": null, "links": []}, {"text": "Good offices of the Secretary-General of the Conference", "type": "paragraph", "language": "english", "heading_level": null, "paragraph_type": "preambular", "paragraph_level": 2, "prefix": "(m)", "action_verb": null, "action_verb_type": null, "action_verb_normalized": null, "links": []}, {"text": "The good offices of the Secretary-General of the Conference shall be utilized as fully as practicable in connexion with the process of conciliation.", "type": "paragraph", "language": "english", "heading_level": null, "paragraph_type": "preambular", "paragraph_level": null, "prefix": null, "action_verb": null, "action_verb_type": null, "action_verb_normalized": null, "links": []}, {"text": "Proposals involving changes in the fundamental provisions of the present resolution", "type": "paragraph", "language": "english", "heading_level": null, "paragraph_type": "preambular", "paragraph_level": 2, "prefix": "(n)", "action_verb": "Proposals", "action_verb_type": "operative", "action_verb_normalized": null, "links": []}, {"text": "A process of conciliation shall also be applied under the terms and conditions laid down above in regard to any proposal for a recommendation to the General Assembly which would involve changes in the fundamental provisions of the present resolution. Any question as to whether a particular provision shall be considered fundamental for the purposes of the present sub-paragraph shall be determined by a simple majority of the Conference or the Board.", "type": "paragraph", "language": "english", "heading_level": null, "paragraph_type": "preambular", "paragraph_level": null, "prefix": null, "action_verb": null, "action_verb_type": null, "action_verb_normalized": null, "links": []}, {"text": "SECRETARIAT", "type": "paragraph", "language": "english", "heading_level": null, "paragraph_type": "preambular", "paragraph_level": null, "prefix": null, "action_verb": null, "action_verb_type": null, "action_verb_normalized": null, "links": []}, {"text": "Arrangements shall be made, in accordance with Article 101 of the Charter, for the immediate establishment of an adequate, permanent and full-time secretariat within the United Nations Secretariat for the proper servicing of the Conference, the Board and its subsidiary bodies.", "type": "paragraph", "language": "english", "heading_level": null, "paragraph_type": "operative", "paragraph_level": 1, "prefix": "26.", "action_verb": "Arrangements", "action_verb_type": "operative", "action_verb_normalized": null, "links": []}, {"text": "The secretariat shall be headed by the Secretary-General of the Conference, who shall be appointed by the Secretary-General of the United Nations and confirmed by the General Assembly.", "type": "paragraph", "language": "english", "heading_level": null, "paragraph_type": "operative", "paragraph_level": 1, "prefix": "27.", "action_verb": null, "action_verb_type": null, "action_verb_normalized": null, "links": []}, {"text": "Adequate arrangements shall be made by the Secretary-General of the United Nations for close co-operation and co-ordination between the secretariat of the Conference and the Department of Economic and Social Affairs, including the secretariats of the regional economic commissions and other appropriate", "type": "paragraph", "language": "english", "heading_level": null, "paragraph_type": "operative", "paragraph_level": 1, "prefix": "28.", "action_verb": null, "action_verb_type": null, "action_verb_normalized": null, "links": []}, {"text": "<!-- Page 5 -->", "type": "footer", "language": "english", "heading_level": null, "paragraph_type": null, "paragraph_level": null, "prefix": null, "action_verb": null, "action_verb_type": null, "action_verb_normalized": null, "links": []}, {"text": "Resolutions adopted without reference to a Committee 5", "type": "paragraph", "language": "english", "heading_level": null, "paragraph_type": "preambular", "paragraph_level": null, "prefix": null, "action_verb": "Resolutions", "action_verb_type": "operative", "action_verb_normalized": null, "links": []}, {"text": "units of the United Nations Secretariat as well as with the secretariats of the specialized agencies.", "type": "paragraph", "language": "english", "heading_level": null, "paragraph_type": "preambular", "paragraph_level": null, "prefix": null, "action_verb": "units", "action_verb_type": "operative", "action_verb_normalized": null, "links": []}, {"text": "FINANCIAL ARRANGEMENTS", "type": "paragraph", "language": "english", "heading_level": null, "paragraph_type": "preambular", "paragraph_level": null, "prefix": null, "action_verb": null, "action_verb_type": null, "action_verb_normalized": null, "links": []}, {"text": "The expenses of the Conference, its subsidiary bodies and secretariat shall be borne by the regular budget of the United Nations, which shall include a separate budgetary provision for such expenses. In accordance with the practice followed by the United Nations in similar cases, arrangements shall be made for assessments on States not members of the United Nations which participate in the Conference.", "type": "paragraph", "language": "english", "heading_level": null, "paragraph_type": "operative", "paragraph_level": 1, "prefix": "29.", "action_verb": null, "action_verb_type": null, "action_verb_normalized": null, "links": []}, {"text": "FUTURE INSTITUTIONAL ARRANGEMENTS", "type": "paragraph", "language": "english", "heading_level": null, "paragraph_type": "preambular", "paragraph_level": null, "prefix": null, "action_verb": null, "action_verb_type": null, "action_verb_normalized": null, "links": []}, {"text": "The Conference will review, in the light of experience, the effectiveness and further evolution of institutional arrangements with a view to recommending such changes and improvements as might be necessary.", "type": "paragraph", "language": "english", "heading_level": null, "paragraph_type": "operative", "paragraph_level": 1, "prefix": "30.", "action_verb": null, "action_verb_type": null, "action_verb_normalized": null, "links": []}, {"text": "To this end the Conference will study all relevant subjects, including matters relating to the establishment of a comprehensive organization based on the entire membership of the United Nations system of organizations to deal with trade and with trade in relation to development.", "type": "paragraph", "language": "english", "heading_level": null, "paragraph_type": "operative", "paragraph_level": 1, "prefix": "31.", "action_verb": null, "action_verb_type": null, "action_verb_normalized": null, "links": []}, {"text": "The General Assembly expresses its intention to seek advice from the Conference before making changes in the fundamental provisions of the present resolution.", "type": "paragraph", "language": "english", "heading_level": null, "paragraph_type": "operative", "paragraph_level": 1, "prefix": "32.", "action_verb": null, "action_verb_type": null, "action_verb_normalized": null, "links": []}, {"text": "1314th plenary meeting,", "type": "backmatter", "language": "english", "heading_level": null, "paragraph_type": null, "paragraph_level": null, "prefix": null, "action_verb": null, "action_verb_type": null, "action_verb_normalized": null, "links": []}, {"text": "30 December 1964.", "type": "backmatter", "language": "english", "heading_level": null, "paragraph_type": null, "paragraph_level": null, "prefix": null, "action_verb": null, "action_verb_type": null, "action_verb_normalized": null, "links": []}, {"text": "  ", "type": "backmatter", "language": "english", "heading_level": null, "paragraph_type": null, "paragraph_level": null, "prefix": null, "action_verb": null, "action_verb_type": null, "action_verb_normalized": null, "links": []}, {"text": "At its 1328th plenary meeting, on 10 February 1965, the General Assembly confirmed the appointment by the Secretary-General, under section II, paragraph 27, of the above resolution, of Dr. Raúl Prebisch as Secretary-General of the United Nations Conference on Trade and Development.", "type": "backmatter", "language": "english", "heading_level": null, "paragraph_type": null, "paragraph_level": null, "prefix": null, "action_verb": null, "action_verb_type": null, "action_verb_normalized": null, "links": []}, {"text": "ANNEX", "type": "backmatter", "language": "english", "heading_level": null, "paragraph_type": null, "paragraph_level": null, "prefix": null, "action_verb": null, "action_verb_type": null, "action_verb_normalized": null, "links": []}, {"text": "List of States indicated in paragraph 5 (a)", "type": "heading", "language": "english", "heading_level": 2, "paragraph_type": null, "paragraph_level": null, "prefix": "A.", "action_verb": null, "action_verb_type": null, "action_verb_normalized": null, "links": []}, {"text": "Afghanistan", "type": "backmatter", "language": "english", "heading_level": null, "paragraph_type": null, "paragraph_level": null, "prefix": null, "action_verb": null, "action_verb_type": null, "action_verb_normalized": null, "links": []}, {"text": "Algeria", "type": "backmatter", "language": "english", "heading_level": null, "paragraph_type": null, "paragraph_level": null, "prefix": null, "action_verb": null, "action_verb_type": null, "action_verb_normalized": null, "links": []}, {"text": "Burma", "type": "backmatter", "language": "english", "heading_level": null, "paragraph_type": null, "paragraph_level": null, "prefix": null, "action_verb": null, "action_verb_type": null, "action_verb_normalized": null, "links": []}, {"text": "Burundi", "type": "backmatter", "language": "english", "heading_level": null, "paragraph_type": null, "paragraph_level": null, "prefix": null, "action_verb": null, "action_verb_type": null, "action_verb_normalized": null, "links": []}, {"text": "Cambodia", "type": "backmatter", "language": "english", "heading_level": null, "paragraph_type": null, "paragraph_level": null, "prefix": null, "action_verb": null, "action_verb_type": null, "action_verb_normalized": null, "links": []}, {"text": "Cameroon", "type": "backmatter", "language": "english", "heading_level": null, "paragraph_type": null, "paragraph_level": null, "prefix": null, "action_verb": null, "action_verb_type": null, "action_verb_normalized": null, "links": []}, {"text": "Central African Republic", "type": "backmatter", "language": "english", "heading_level": null, "paragraph_type": null, "paragraph_level": null, "prefix": null, "action_verb": null, "action_verb_type": null, "action_verb_normalized": null, "links": []}, {"text": "Ceylon", "type": "backmatter", "language": "english", "heading_level": null, "paragraph_type": null, "paragraph_level": null, "prefix": null, "action_verb": null, "action_verb_type": null, "action_verb_normalized": null, "links": []}, {"text": "Chad", "type": "backmatter", "language": "english", "heading_level": null, "paragraph_type": null, "paragraph_level": null, "prefix": null, "action_verb": null, "action_verb_type": null, "action_verb_normalized": null, "links": []}, {"text": "China", "type": "backmatter", "language": "english", "heading_level": null, "paragraph_type": null, "paragraph_level": null, "prefix": null, "action_verb": null, "action_verb_type": null, "action_verb_normalized": null, "links": []}, {"text": "Congo (Brazzaville)", "type": "backmatter", "language": "english", "heading_level": null, "paragraph_type": null, "paragraph_level": null, "prefix": null, "action_verb": null, "action_verb_type": null, "action_verb_normalized": null, "links": []}, {"text": "Congo (Democratic Republic of)", "type": "backmatter", "language": "english", "heading_level": null, "paragraph_type": null, "paragraph_level": null, "prefix": null, "action_verb": null, "action_verb_type": null, "action_verb_normalized": null, "links": []}, {"text": "Dahomey", "type": "backmatter", "language": "english", "heading_level": null, "paragraph_type": null, "paragraph_level": null, "prefix": null, "action_verb": null, "action_verb_type": null, "action_verb_normalized": null, "links": []}, {"text": "Ethiopia", "type": "backmatter", "language": "english", "heading_level": null, "paragraph_type": null, "paragraph_level": null, "prefix": null, "action_verb": null, "action_verb_type": null, "action_verb_normalized": null, "links": []}, {"text": "Gabon", "type": "backmatter", "language": "english", "heading_level": null, "paragraph_type": null, "paragraph_level": null, "prefix": null, "action_verb": null, "action_verb_type": null, "action_verb_normalized": null, "links": []}, {"text": "Ghana", "type": "backmatter", "language": "english", "heading_level": null, "paragraph_type": null, "paragraph_level": null, "prefix": null, "action_verb": null, "action_verb_type": null, "action_verb_normalized": null, "links": []}, {"text": "Guinea", "type": "backmatter", "language": "english", "heading_level": null, "paragraph_type": null, "paragraph_level": null, "prefix": null, "action_verb": null, "action_verb_type": null, "action_verb_normalized": null, "links": []}, {"text": "India", "type": "backmatter", "language": "english", "heading_level": null, "paragraph_type": null, "paragraph_level": null, "prefix": null, "action_verb": null, "action_verb_type": null, "action_verb_normalized": null, "links": []}, {"text": "Indonesia", "type": "backmatter", "language": "english", "heading_level": null, "paragraph_type": null, "paragraph_level": null, "prefix": null, "action_verb": null, "action_verb_type": null, "action_verb_normalized": null, "links": []}, {"text": "Iran", "type": "backmatter", "language": "english", "heading_level": null, "paragraph_type": null, "paragraph_level": null, "prefix": null, "action_verb": null, "action_verb_type": null, "action_verb_normalized": null, "links": []}, {"text": "Iraq", "type": "backmatter", "language": "english", "heading_level": null, "paragraph_type": null, "paragraph_level": null, "prefix": null, "action_verb": null, "action_verb_type": null, "action_verb_normalized": null, "links": []}, {"text": "Israel", "type": "backmatter", "language": "english", "heading_level": null, "paragraph_type": null, "paragraph_level": null, "prefix": null, "action_verb": null, "action_verb_type": null, "action_verb_normalized": null, "links": []}, {"text": "Ivory Coast", "type": "backmatter", "language": "english", "heading_level": null, "paragraph_type": null, "paragraph_level": null, "prefix": null, "action_verb": null, "action_verb_type": null, "action_verb_normalized": null, "links": []}, {"text": "Jordan", "type": "backmatter", "language": "english", "heading_level": null, "paragraph_type": null, "paragraph_level": null, "prefix": null, "action_verb": null, "action_verb_type": null, "action_verb_normalized": null, "links": []}, {"text": "Kenya", "type": "backmatter", "language": "english", "heading_level": null, "paragraph_type": null, "paragraph_level": null, "prefix": null, "action_verb": null, "action_verb_type": null, "action_verb_normalized": null, "links": []}, {"text": "Kuwait", "type": "backmatter", "language": "english", "heading_level": null, "paragraph_type": null, "paragraph_level": null, "prefix": null, "action_verb": null, "action_verb_type": null, "action_verb_normalized": null, "links": []}, {"text": "Laos", "type": "backmatter", "language": "english", "heading_level": null, "paragraph_type": null, "paragraph_level": null, "prefix": null, "action_verb": null, "action_verb_type": null, "action_verb_normalized": null, "links": []}, {"text": "Lebanon", "type": "backmatter", "language": "english", "heading_level": null, "paragraph_type": null, "paragraph_level": null, "prefix": null, "action_verb": null, "action_verb_type": null, "action_verb_normalized": null, "links": []}, {"text": "Liberia", "type": "backmatter", "language": "english", "heading_level": null, "paragraph_type": null, "paragraph_level": null, "prefix": null, "action_verb": null, "action_verb_type": null, "action_verb_normalized": null, "links": []}, {"text": "Libya", "type": "backmatter", "language": "english", "heading_level": null, "paragraph_type": null, "paragraph_level": null, "prefix": null, "action_verb": null, "action_verb_type": null, "action_verb_normalized": null, "links": []}, {"text": "Madagascar", "type": "backmatter", "language": "english", "heading_level": null, "paragraph_type": null, "paragraph_level": null, "prefix": null, "action_verb": null, "action_verb_type": null, "action_verb_normalized": null, "links": []}, {"text": "Malaysia", "type": "backmatter", "language": "english", "heading_level": null, "paragraph_type": null, "paragraph_level": null, "prefix": null, "action_verb": null, "action_verb_type": null, "action_verb_normalized": null, "links": []}, {"text": "Mali", "type": "backmatter", "language": "english", "heading_level": null, "paragraph_type": null, "paragraph_level": null, "prefix": null, "action_verb": null, "action_verb_type": null, "action_verb_normalized": null, "links": []}, {"text": "Mauritania", "type": "backmatter", "language": "english", "heading_level": null, "paragraph_type": null, "paragraph_level": null, "prefix": null, "action_verb": null, "action_verb_type": null, "action_verb_normalized": null, "links": []}, {"text": "Mongolia", "type": "backmatter", "language": "english", "heading_level": null, "paragraph_type": null, "paragraph_level": null, "prefix": null, "action_verb": null, "action_verb_type": null, "action_verb_normalized": null, "links": []}, {"text": "Morocco", "type": "backmatter", "language": "english", "heading_level": null, "paragraph_type": null, "paragraph_level": null, "prefix": null, "action_verb": null, "action_verb_type": null, "action_verb_normalized": null, "links": []}, {"text": "Nepal", "type": "backmatter", "language": "english", "heading_level": null, "paragraph_type": null, "paragraph_level": null, "prefix": null, "action_verb": null, "action_verb_type": null, "action_verb_normalized": null, "links": []}, {"text": "Niger", "type": "backmatter", "language": "english", "heading_level": null, "paragraph_type": null, "paragraph_level": null, "prefix": null, "action_verb": null, "action_verb_type": null, "action_verb_normalized": null, "links": []}, {"text": "Nigeria", "type": "backmatter", "language": "english", "heading_level": null, "paragraph_type": null, "paragraph_level": null, "prefix": null, "action_verb": null, "action_verb_type": null, "action_verb_normalized": null, "links": []}, {"text": "Pakistan", "type": "backmatter", "language": "english", "heading_level": null, "paragraph_type": null, "paragraph_level": null, "prefix": null, "action_verb": null, "action_verb_type": null, "action_verb_normalized": null, "links": []}, {"text": "Philippines", "type": "backmatter", "language": "english", "heading_level": null, "paragraph_type": null, "paragraph_level": null, "prefix": null, "action_verb": null, "action_verb_type": null, "action_verb_normalized": null, "links": []}, {"text": "Republic of Korea", "type": "backmatter", "language": "english", "heading_level": null, "paragraph_type": null, "paragraph_level": null, "prefix": null, "action_verb": null, "action_verb_type": null, "action_verb_normalized": null, "links": []}, {"text": "Republic of Viet-Nam", "type": "backmatter", "language": "english", "heading_level": null, "paragraph_type": null, "paragraph_level": null, "prefix": null, "action_verb": null, "action_verb_type": null, "action_verb_normalized": null, "links": []}, {"text": "Rwanda", "type": "backmatter", "language": "english", "heading_level": null, "paragraph_type": null, "paragraph_level": null, "prefix": null, "action_verb": null, "action_verb_type": null, "action_verb_normalized": null, "links": []}, {"text": "Saudi Arabia", "type": "backmatter", "language": "english", "heading_level": null, "paragraph_type": null, "paragraph_level": null, "prefix": null, "action_verb": null, "action_verb_type": null, "action_verb_normalized": null, "links": []}, {"text": "Senegal", "type": "backmatter", "language": "english", "heading_level": null, "paragraph_type": null, "paragraph_level": null, "prefix": null, "action_verb": null, "action_verb_type": null, "action_verb_normalized": null, "links": []}, {"text": "Sierra Leone", "type": "backmatter", "language": "english", "heading_level": null, "paragraph_type": null, "paragraph_level": null, "prefix": null, "action_verb": null, "action_verb_type": null, "action_verb_normalized": null, "links": []}, {"text": "Somalia", "type": "backmatter", "language": "english", "heading_level": null, "paragraph_type": null, "paragraph_level": null, "prefix": null, "action_verb": null, "action_verb_type": null, "action_verb_normalized": null, "links": []}, {"text": "South Africa", "type": "backmatter", "language": "english", "heading_level": null, "paragraph_type": null, "paragraph_level": null, "prefix": null, "action_verb": null, "action_verb_type": null, "action_verb_normalized": null, "links": []}, {"text": "Sudan", "type": "backmatter", "language": "english", "heading_level": null, "paragraph_type": null, "paragraph_level": null, "prefix": null, "action_verb": null, "action_verb_type": null, "action_verb_normalized": null, "links": []}, {"text": "Syria", "type": "backmatter", "language": "english", "heading_level": null, "paragraph_type": null, "paragraph_level": null, "prefix": null, "action_verb": null, "action_verb_type": null, "action_verb_normalized": null, "links": []}, {"text": "Thailand", "type": "backmatter", "language": "english", "heading_level": null, "paragraph_type": null, "paragraph_level": null, "prefix": null, "action_verb": null, "action_verb_type": null, "action_verb_normalized": null, "links": []}, {"text": "Togo", "type": "backmatter", "language": "english", "heading_level": null, "paragraph_type": null, "paragraph_level": null, "prefix": null, "action_verb": null, "action_verb_type": null, "action_verb_normalized": null, "links": []}, {"text": "Tunisia", "type": "backmatter", "language": "english", "heading_level": null, "paragraph_type": null, "paragraph_level": null, "prefix": null, "action_verb": null, "action_verb_type": null, "action_verb_normalized": null, "links": []}, {"text": "Uganda", "type": "backmatter", "language": "english", "heading_level": null, "paragraph_type": null, "paragraph_level": null, "prefix": null, "action_verb": null, "action_verb_type": null, "action_verb_normalized": null, "links": []}, {"text": "United Arab Republic", "type": "backmatter", "language": "english", "heading_level": null, "paragraph_type": null, "paragraph_level": null, "prefix": null, "action_verb": null, "action_verb_type": null, "action_verb_normalized": null, "links": []}, {"text": "United Republic of Tanzania", "type": "backmatter", "language": "english", "heading_level": null, "paragraph_type": null, "paragraph_level": null, "prefix": null, "action_verb": null, "action_verb_type": null, "action_verb_normalized": null, "links": []}, {"text": "Upper Volta", "type": "backmatter", "language": "english", "heading_level": null, "paragraph_type": null, "paragraph_level": null, "prefix": null, "action_verb": null, "action_verb_type": null, "action_verb_normalized": null, "links": []}, {"text": "Western Samoa", "type": "backmatter", "language": "english", "heading_level": null, "paragraph_type": null, "paragraph_level": null, "prefix": null, "action_verb": null, "action_verb_type": null, "action_verb_normalized": null, "links": []}, {"text": "Yemen", "type": "backmatter", "language": "english", "heading_level": null, "paragraph_type": null, "paragraph_level": null, "prefix": null, "action_verb": null, "action_verb_type": null, "action_verb_normalized": null, "links": []}, {"text": "Yugoslavia", "type": "backmatter", "language": "english", "heading_level": null, "paragraph_type": null, "paragraph_level": null, "prefix": null, "action_verb": null, "action_verb_type": null, "action_verb_normalized": null, "links": []}, {"text": "List of States indicated in paragraph 5 (b)", "type": "heading", "language": "english", "heading_level": 2, "paragraph_type": null, "paragraph_level": null, "prefix": "B.", "action_verb": null, "action_verb_type": null, "action_verb_normalized": null, "links": []}, {"text": "Australia", "type": "backmatter", "language": "english", "heading_level": null, "paragraph_type": null, "paragraph_level": null, "prefix": null, "action_verb": null, "action_verb_type": null, "action_verb_normalized": null, "links": []}, {"text": "Austria", "type": "backmatter", "language": "english", "heading_level": null, "paragraph_type": null, "paragraph_level": null, "prefix": null, "action_verb": null, "action_verb_type": null, "action_verb_normalized": null, "links": []}, {"text": "Belgium", "type": "backmatter", "language": "english", "heading_level": null, "paragraph_type": null, "paragraph_level": null, "prefix": null, "action_verb": null, "action_verb_type": null, "action_verb_normalized": null, "links": []}, {"text": "Canada", "type": "backmatter", "language": "english", "heading_level": null, "paragraph_type": null, "paragraph_level": null, "prefix": null, "action_verb": null, "action_verb_type": null, "action_verb_normalized": null, "links": []}, {"text": "Cyprus", "type": "backmatter", "language": "english", "heading_level": null, "paragraph_type": null, "paragraph_level": null, "prefix": null, "action_verb": null, "action_verb_type": null, "action_verb_normalized": null, "links": []}, {"text": "Denmark", "type": "backmatter", "language": "english", "heading_level": null, "paragraph_type": null, "paragraph_level": null, "prefix": null, "action_verb": null, "action_verb_type": null, "action_verb_normalized": null, "links": []}, {"text": "Federal Republic of Germany", "type": "backmatter", "language": "english", "heading_level": null, "paragraph_type": null, "paragraph_level": null, "prefix": null, "action_verb": null, "action_verb_type": null, "action_verb_normalized": null, "links": []}, {"text": "Finland", "type": "backmatter", "language": "english", "heading_level": null, "paragraph_type": null, "paragraph_level": null, "prefix": null, "action_verb": null, "action_verb_type": null, "action_verb_normalized": null, "links": []}, {"text": "France", "type": "backmatter", "language": "english", "heading_level": null, "paragraph_type": null, "paragraph_level": null, "prefix": null, "action_verb": null, "action_verb_type": null, "action_verb_normalized": null, "links": []}, {"text": "Greece", "type": "backmatter", "language": "english", "heading_level": null, "paragraph_type": null, "paragraph_level": null, "prefix": null, "action_verb": null, "action_verb_type": null, "action_verb_normalized": null, "links": []}, {"text": "Holy See", "type": "backmatter", "language": "english", "heading_level": null, "paragraph_type": null, "paragraph_level": null, "prefix": null, "action_verb": null, "action_verb_type": null, "action_verb_normalized": null, "links": []}, {"text": "Iceland", "type": "backmatter", "language": "english", "heading_level": null, "paragraph_type": null, "paragraph_level": null, "prefix": null, "action_verb": null, "action_verb_type": null, "action_verb_normalized": null, "links": []}, {"text": "Ireland", "type": "backmatter", "language": "english", "heading_level": null, "paragraph_type": null, "paragraph_level": null, "prefix": null, "action_verb": null, "action_verb_type": null, "action_verb_normalized": null, "links": []}, {"text": "Italy", "type": "backmatter", "language": "english", "heading_level": null, "paragraph_type": null, "paragraph_level": null, "prefix": null, "action_verb": null, "action_verb_type": null, "action_verb_normalized": null, "links": []}, {"text": "Japan", "type": "backmatter", "language": "english", "heading_level": null, "paragraph_type": null, "paragraph_level": null, "prefix": null, "action_verb": null, "action_verb_type": null, "action_verb_normalized": null, "links": []}, {"text": "Liechtenstein", "type": "backmatter", "language": "english", "heading_level": null, "paragraph_type": null, "paragraph_level": null, "prefix": null, "action_verb": null, "action_verb_type": null, "action_verb_normalized": null, "links": []}, {"text": "Luxembourg", "type": "backmatter", "language": "english", "heading_level": null, "paragraph_type": null, "paragraph_level": null, "prefix": null, "action_verb": null, "action_verb_type": null, "action_verb_normalized": null, "links": []}, {"text": "Monaco", "type": "backmatter", "language": "english", "heading_level": null, "paragraph_type": null, "paragraph_level": null, "prefix": null, "action_verb": null, "action_verb_type": null, "action_verb_normalized": null, "links": []}, {"text": "Netherlands", "type": "backmatter", "language": "english", "heading_level": null, "paragraph_type": null, "paragraph_level": null, "prefix": null, "action_verb": null, "action_verb_type": null, "action_verb_normalized": null, "links": []}, {"text": "New Zealand", "type": "backmatter", "language": "english", "heading_level": null, "paragraph_type": null, "paragraph_level": null, "prefix": null, "action_verb": null, "action_verb_type": null, "action_verb_normalized": null, "links": []}, {"text": "Norway", "type": "backmatter", "language": "english", "heading_level": null, "paragraph_type": null, "paragraph_level": null, "prefix": null, "action_verb": null, "action_verb_type": null, "action_verb_normalized": null, "links": []}, {"text": "Portugal", "type": "backmatter", "language": "english", "heading_level": null, "paragraph_type": null, "paragraph_level": null, "prefix": null, "action_verb": null, "action_verb_type": null, "action_verb_normalized": null, "links": []}, {"text": "San Marino", "type": "backmatter", "language": "english", "heading_level": null, "paragraph_type": null, "paragraph_level": null, "prefix": null, "action_verb": null, "action_verb_type": null, "action_verb_normalized": null, "links": []}, {"text": "Spain", "type": "backmatter", "language": "english", "heading_level": null, "paragraph_type": null, "paragraph_level": null, "prefix": null, "action_verb": null, "action_verb_type": null, "action_verb_normalized": null, "links": []}, {"text": "Sweden", "type": "backmatter", "language": "english", "heading_level": null, "paragraph_type": null, "paragraph_level": null, "prefix": null, "action_verb": null, "action_verb_type": null, "action_verb_normalized": null, "links": []}, {"text": "Switzerland", "type": "backmatter", "language": "english", "heading_level": null, "paragraph_type": null, "paragraph_level": null, "prefix": null, "action_verb": null, "action_verb_type": null, "action_verb_normalized": null, "links": []}, {"text": "Turkey", "type": "backmatter", "language": "english", "heading_level": null, "paragraph_type": null, "paragraph_level": null, "prefix": null, "action_verb": null, "action_verb_type": null, "action_verb_normalized": null, "links": []}, {"text": "United Kingdom of Great Britain and Northern Ireland", "type": "backmatter", "language": "english", "heading_level": null, "paragraph_type": null, "paragraph_level": null, "prefix": null, "action_verb": null, "action_verb_type": null, "action_verb_normalized": null, "links": []}, {"text": "United States of America", "type": "backmatter", "language": "english", "heading_level": null, "paragraph_type": null, "paragraph_level": null, "prefix": null, "action_verb": null, "action_verb_type": null, "action_verb_normalized": null, "links": []}, {"text": "List of States indicated in paragraph 5 (c)", "type": "heading", "language": "english", "heading_level": 2, "paragraph_type": null, "paragraph_level": null, "prefix": "C.", "action_verb": null, "action_verb_type": null, "action_verb_normalized": null, "links": []}, {"text": "Argentina", "type": "backmatter", "language": "english", "heading_level": null, "paragraph_type": null, "paragraph_level": null, "prefix": null, "action_verb": null, "action_verb_type": null, "action_verb_normalized": null, "links": []}, {"text": "Bolivia", "type": "backmatter", "language": "english", "heading_level": null, "paragraph_type": null, "paragraph_level": null, "prefix": null, "action_verb": null, "action_verb_type": null, "action_verb_normalized": null, "links": []}, {"text": "Brazil", "type": "backmatter", "language": "english", "heading_level": null, "paragraph_type": null, "paragraph_level": null, "prefix": null, "action_verb": null, "action_verb_type": null, "action_verb_normalized": null, "links": []}, {"text": "Chile", "type": "backmatter", "language": "english", "heading_level": null, "paragraph_type": null, "paragraph_level": null, "prefix": null, "action_verb": null, "action_verb_type": null, "action_verb_normalized": null, "links": []}, {"text": "Colombia", "type": "backmatter", "language": "english", "heading_level": null, "paragraph_type": null, "paragraph_level": null, "prefix": null, "action_verb": null, "action_verb_type": null, "action_verb_normalized": null, "links": []}, {"text": "Costa Rica", "type": "backmatter", "language": "english", "heading_level": null, "paragraph_type": null, "paragraph_level": null, "prefix": null, "action_verb": null, "action_verb_type": null, "action_verb_normalized": null, "links": []}, {"text": "Cuba", "type": "backmatter", "language": "english", "heading_level": null, "paragraph_type": null, "paragraph_level": null, "prefix": null, "action_verb": null, "action_verb_type": null, "action_verb_normalized": null, "links": []}, {"text": "Dominican Republic", "type": "backmatter", "language": "english", "heading_level": null, "paragraph_type": null, "paragraph_level": null, "prefix": null, "action_verb": null, "action_verb_type": null, "action_verb_normalized": null, "links": []}, {"text": "Ecuador", "type": "backmatter", "language": "english", "heading_level": null, "paragraph_type": null, "paragraph_level": null, "prefix": null, "action_verb": null, "action_verb_type": null, "action_verb_normalized": null, "links": []}, {"text": "El Salvador", "type": "backmatter", "language": "english", "heading_level": null, "paragraph_type": null, "paragraph_level": null, "prefix": null, "action_verb": null, "action_verb_type": null, "action_verb_normalized": null, "links": []}, {"text": "Guatemala", "type": "backmatter", "language": "english", "heading_level": null, "paragraph_type": null, "paragraph_level": null, "prefix": null, "action_verb": null, "action_verb_type": null, "action_verb_normalized": null, "links": []}, {"text": "Haiti", "type": "backmatter", "language": "english", "heading_level": null, "paragraph_type": null, "paragraph_level": null, "prefix": null, "action_verb": null, "action_verb_type": null, "action_verb_normalized": null, "links": []}, {"text": "Honduras", "type": "backmatter", "language": "english", "heading_level": null, "paragraph_type": null, "paragraph_level": null, "prefix": null, "action_verb": null, "action_verb_type": null, "action_verb_normalized": null, "links": []}, {"text": "Jamaica", "type": "backmatter", "language": "english", "heading_level": null, "paragraph_type": null, "paragraph_level": null, "prefix": null, "action_verb": null, "action_verb_type": null, "action_verb_normalized": null, "links": []}, {"text": "Mexico", "type": "backmatter", "language": "english", "heading_level": null, "paragraph_type": null, "paragraph_level": null, "prefix": null, "action_verb": null, "action_verb_type": null, "action_verb_normalized": null, "links": []}, {"text": "Nicaragua", "type": "backmatter", "language": "english", "heading_level": null, "paragraph_type": null, "paragraph_level": null, "prefix": null, "action_verb": null, "action_verb_type": null, "action_verb_normalized": null, "links": []}, {"text": "Panama", "type": "backmatter", "language": "english", "heading_level": null, "paragraph_type": null, "paragraph_level": null, "prefix": null, "action_verb": null, "action_verb_type": null, "action_verb_normalized": null, "links": []}, {"text": "Paraguay", "type": "backmatter", "language": "english", "heading_level": null, "paragraph_type": null, "paragraph_level": null, "prefix": null, "action_verb": null, "action_verb_type": null, "action_verb_normalized": null, "links": []}, {"text": "Peru", "type": "backmatter", "language": "english", "heading_level": null, "paragraph_type": null, "paragraph_level": null, "prefix": null, "action_verb": null, "action_verb_type": null, "action_verb_normalized": null, "links": []}, {"text": "Trinidad and Tobago", "type": "backmatter", "language": "english", "heading_level": null, "paragraph_type": null, "paragraph_level": null, "prefix": null, "action_verb": null, "action_verb_type": null, "action_verb_normalized": null, "links": []}, {"text": "Uruguay", "type": "backmatter", "language": "english", "heading_level": null, "paragraph_type": null, "paragraph_level": null, "prefix": null, "action_verb": null, "action_verb_type": null, "action_verb_normalized": null, "links": []}, {"text": "Venezuela", "type": "backmatter", "language": "english", "heading_level": null, "paragraph_type": null, "paragraph_level": null, "prefix": null, "action_verb": null, "action_verb_type": null, "action_verb_normalized": null, "links": []}, {"text": "List of States indicated in paragraph 5 (d)", "type": "heading", "language": "english", "heading_level": 2, "paragraph_type": null, "paragraph_level": null, "prefix": "D.", "action_verb": null, "action_verb_type": null, "action_verb_normalized": null, "links": []}, {"text": "Albania", "type": "backmatter", "language": "english", "heading_level": null, "paragraph_type": null, "paragraph_level": null, "prefix": null, "action_verb": null, "action_verb_type": null, "action_verb_normalized": null, "links": []}, {"text": "Bulgaria", "type": "backmatter", "language": "english", "heading_level": null, "paragraph_type": null, "paragraph_level": null, "prefix": null, "action_verb": null, "action_verb_type": null, "action_verb_normalized": null, "links": []}, {"text": "Byelorussian Soviet Socialist Republic", "type": "backmatter", "language": "english", "heading_level": null, "paragraph_type": null, "paragraph_level": null, "prefix": null, "action_verb": null, "action_verb_type": null, "action_verb_normalized": null, "links": []}, {"text": "Czechoslovakia", "type": "backmatter", "language": "english", "heading_level": null, "paragraph_type": null, "paragraph_level": null, "prefix": null, "action_verb": null, "action_verb_type": null, "action_verb_normalized": null, "links": []}, {"text": "Hungary", "type": "backmatter", "language": "english", "heading_level": null, "paragraph_type": null, "paragraph_level": null, "prefix": null, "action_verb": null, "action_verb_type": null, "action_verb_normalized": null, "links": []}, {"text": "Poland", "type": "backmatter", "language": "english", "heading_level": null, "paragraph_type": null, "paragraph_level": null, "prefix": null, "action_verb": null, "action_verb_type": null, "action_verb_normalized": null, "links": []}, {"text": "Romania", "type": "backmatter", "language": "english", "heading_level": null, "paragraph_type": null, "paragraph_level": null, "prefix": null, "action_verb": null, "action_verb_type": null, "action_verb_normalized": null, "links": []}, {"text": "Ukrainian Soviet Socialist Republic", "type": "backmatter", "language": "english", "heading_level": null, "paragraph_type": null, "paragraph_level": null, "prefix": null, "action_verb": null, "action_verb_type": null, "action_verb_normalized": null, "links": []}, {"text": "Union of Soviet Socialist Republics", "type": "backmatter", "language": "english", "heading_level": null, "paragraph_type": null, "paragraph_level": null, "prefix": null, "action_verb": null, "action_verb_type": null, "action_verb_normalized": null, "links": []}, {"text": "1996 (XIX). Appointments to fill vacancies in the membership of the Advisory Committee on Administrative and Budgetary Questions", "type": "backmatter", "language": "english", "heading_level": null, "paragraph_type": null, "paragraph_level": null, "prefix": null, "action_verb": null, "action_verb_type": null, "action_verb_normalized": null, "links": []}, {"text": "The General Assembly", "type": "backmatter", "language": "english", "heading_level": null, "paragraph_type": null, "paragraph_level": null, "prefix": null, "action_verb": null, "action_verb_type": null, "action_verb_normalized": null, "links": []}, {"text": "1. Appoints the following persons as members of the Advisory Committee on Administrative and Budgetary Questions:", "type": "backmatter", "language": "english", "heading_level": null, "paragraph_type": null, "paragraph_level": null, "prefix": null, "action_verb": null, "action_verb_type": null, "action_verb_normalized": null, "links": []}, {"text": "Mr. Paulo Lopes Corrêa,", "type": "backmatter", "language": "english", "heading_level": null, "paragraph_type": null, "paragraph_level": null, "prefix": null, "action_verb": null, "action_verb_type": null, "action_verb_normalized": null, "links": []}, {"text": "Mr. Mohamed Riad,", "type": "backmatter", "language": "english", "heading_level": null, "paragraph_type": null, "paragraph_level": null, "prefix": null, "action_verb": null, "action_verb_type": null, "action_verb_normalized": null, "links": []}, {"text": "Mr. E. Olu Sanu,", "type": "backmatter", "language": "english", "heading_level": null, "paragraph_type": null, "paragraph_level": null, "prefix": null, "action_verb": null, "action_verb_type": null, "action_verb_normalized": null, "links": []}, {"text": "Mr. Dragos Serbanescu;", "type": "backmatter", "language": "english", "heading_level": null, "paragraph_type": null, "paragraph_level": null, "prefix": null, "action_verb": null, "action_verb_type": null, "action_verb_normalized": null, "links": []}, {"text": "2. Declares Mr. Corrêa, Mr. Riad, Mr. Sanu and Mr. Serbanescu to be appointed for a three-year term beginning on 1 January 1965.", "type": "backmatter", "language": "english", "heading_level": null, "paragraph_type": null, "paragraph_level": null, "prefix": null, "action_verb": null, "action_verb_type": null, "action_verb_normalized": null, "links": []}, {"text": "1328th plenary meeting,", "type": "backmatter", "language": "english", "heading_level": null, "paragraph_type": null, "paragraph_level": null, "prefix": null, "action_verb": null, "action_verb_type": null, "action_verb_normalized": null, "links": []}, {"text": "10 February 1965.", "type": "backmatter", "language": "english", "heading_level": null, "paragraph_type": null, "paragraph_level": null, "prefix": null, "action_verb": null, "action_verb_type": null, "action_verb_normalized": null, "links": []}, {"text": "  ", "type": "backmatter", "language": "english", "heading_level": null, "paragraph_type": null, "paragraph_level": null, "prefix": null, "action_verb": null, "action_verb_type": null, "action_verb_normalized": null, "links": []}, {"text": "As a result of the above appointments, the Advisory Committee on Administrative and Budgetary Questions will be composed as follows: Mr. Jan P. BANNER (Netherlands), Mr. Albert F. BENNIK (United States of America), Mr. Raouf BOUJRAKDJI (Algeria), Mr. Paulo Lopes CORRÊA (Brazil), Mr. André GANEM (France), Mr. James GINSON (United Kingdom of Great Britain and Northern Ireland), Mr. Raúl A. J. QUIJANO (Argentina), Mr. Mohamed RIAD (United Arab Republic), Mr. E. Olu SANU (Nigeria), Mr. Dragos SERBANESCU (Romania), Mr. Agha SHAHI (Pakistan) and Mr. V. F. ULANCHEV (Union of Soviet Socialist Republics).", "type": "backmatter", "language": "english", "heading_level": null, "paragraph_type": null, "paragraph_level": null, "prefix": null, "action_verb": null, "action_verb_type": null, "action_verb_normalized": null, "links": []}]